odoo8_addon_stock_lot_quantity-8.0.1.0.0.99.dev6-py2.7-nspkg.pth
odoo8_addon_stock_lot_quantity-8.0.1.0.0.99.dev6.dist-info/METADATA
odoo8_addon_stock_lot_quantity-8.0.1.0.0.99.dev6.dist-info/RECORD
odoo8_addon_stock_lot_quantity-8.0.1.0.0.99.dev6.dist-info/WHEEL
odoo8_addon_stock_lot_quantity-8.0.1.0.0.99.dev6.dist-info/namespace_packages.txt
odoo8_addon_stock_lot_quantity-8.0.1.0.0.99.dev6.dist-info/top_level.txt
odoo_addons/stock_lot_quantity/README.rst
odoo_addons/stock_lot_quantity/__init__.py
odoo_addons/stock_lot_quantity/__openerp__.py
odoo_addons/stock_lot_quantity/i18n/de.po
odoo_addons/stock_lot_quantity/i18n/es.po
odoo_addons/stock_lot_quantity/i18n/fr.po
odoo_addons/stock_lot_quantity/i18n/gl.po
odoo_addons/stock_lot_quantity/i18n/it.po
odoo_addons/stock_lot_quantity/i18n/pt_BR.po
odoo_addons/stock_lot_quantity/i18n/sl.po
odoo_addons/stock_lot_quantity/i18n/stock_lot_quantity.pot
odoo_addons/stock_lot_quantity/models/__init__.py
odoo_addons/stock_lot_quantity/models/stock_production_lot.py
odoo_addons/stock_lot_quantity/static/description/icon.png
odoo_addons/stock_lot_quantity/tests/__init__.py
odoo_addons/stock_lot_quantity/tests/test_lot_quantity.py
odoo_addons/stock_lot_quantity/views/stock_production_lot_view.xml
